LICENSE.txt
MANIFEST.in
README.rst
requirements.txt
setup.cfg
setup.py
cassette/__init__.py
cassette/cassette_library.py
cassette/config.py
cassette/http_connection.py
cassette/http_response.py
cassette/mocked_response.py
cassette/patcher.py
cassette/player.py
cassette/unpatched.py
cassette/utils.py
cassette.egg-info/PKG-INFO
cassette.egg-info/SOURCES.txt
cassette.egg-info/dependency_links.txt
cassette.egg-info/not-zip-safe
cassette.egg-info/requires.txt
cassette.egg-info/top_level.txt
cassette/tests/__init__.py
cassette/tests/base.py
cassette/tests/test_cassette.py
cassette/tests/test_cassette_library.py
cassette/tests/test_cassette_performance.py
cassette/tests/test_cassette_utils.py
cassette/tests/server/__init__.py
cassette/tests/server/run.py
cassette/tests/use_cases/__init__.py
cassette/tests/use_cases/test_report_unused.py