Metadata-Version: 1.1
Name: cassette
Version: 0.3.8
Summary: Cassette stores and replays HTTP requests.
Home-page: http://cassette.readthedocs.org/
Author: Charles-Axel Dein
Author-email: charles@uber.com
License: MIT
Keywords: http,tests,mock
Platform: UNKNOWN
Classifier: Development Status :: 3 - Alpha
Classifier: Environment :: Web Environment
Classifier: Programming Language :: Python
Classifier: Programming Language :: Python :: 2.7
Classifier: Intended Audience :: Developers
Classifier: License :: OSI Approved :: MIT License
Classifier: Operating System :: OS Independent
Classifier: Topic :: Internet :: WWW/HTTP
Classifier: Topic :: Software Development :: Testing
Classifier: Topic :: Software Development :: Libraries :: Python Modules
